bob/__init__.py
bob/pad/__init__.py
bob/pad/face/__init__.py
bob/pad/face/deep_pix_bis.py
bob/pad/face/config/__init__.py
bob/pad/face/config/casia_fasd.py
bob/pad/face/config/casia_surf.py
bob/pad/face/config/deep_pix_bis.py
bob/pad/face/config/lbp_svm.py
bob/pad/face/config/mask_attack.py
bob/pad/face/config/oulu_npu.py
bob/pad/face/config/replay_attack.py
bob/pad/face/config/replay_mobile.py
bob/pad/face/config/swan.py
bob/pad/face/database/__init__.py
bob/pad/face/database/casia_fasd.py
bob/pad/face/database/casia_surf.py
bob/pad/face/database/database.py
bob/pad/face/database/mask_attack.py
bob/pad/face/database/oulu_npu.py
bob/pad/face/database/replay_attack.py
bob/pad/face/database/replay_mobile.py
bob/pad/face/database/swan.py
bob/pad/face/extractor/__init__.py
bob/pad/face/preprocessor/Patch.py
bob/pad/face/preprocessor/__init__.py
bob/pad/face/script/__init__.py
bob/pad/face/script/statistics.py
bob/pad/face/transformer/VideoToFrames.py
bob/pad/face/transformer/__init__.py
bob/pad/face/transformer/histogram.py
bob/pad/face/utils/__init__.py
bob/pad/face/utils/load_utils.py
bob.pad.face-5.0.2.dist-info/COPYING
bob.pad.face-5.0.2.dist-info/METADATA
bob.pad.face-5.0.2.dist-info/WHEEL
bob.pad.face-5.0.2.dist-info/entry_points.txt
bob.pad.face-5.0.2.dist-info/top_level.txt
bob.pad.face-5.0.2.dist-info/RECORD
